troop/__init__.py
troop/api.py
troop/base.py
troop/clients/__init__.py
troop/clients/command.py
troop/clients/file_manage.py
troop/clients/file_send.py
troop/clients/host.py
troop/clients/ping.py
troop/clients/plugin.py
troop/clients/result.py
troop_sdk-0.1.1.dist-info/METADATA
troop_sdk-0.1.1.dist-info/WHEEL
troop_sdk-0.1.1.dist-info/top_level.txt
troop_sdk-0.1.1.dist-info/RECORD
