Metadata-Version: 2.1
Name: troop-sdk
Version: 0.1.1
Summary: UNKNOWN
Home-page: https://github.com/troopstack/troop-sdk.git
License: UNKNOWN
Platform: UNKNOWN
